{
  "batch_id": "batch_20251002_100800",
  "start_time": "2025-10-02T10:08:00+02:00",
  "campaign": "lv4d_campaign_2025",
  "total_experiments": 7,
  "sessions": [
    {
      "session_name": "minimal_4d_lv_test_GN=5_domain_size_param=0.1_max_time=45.0_20251002_100800",
      "parameters": {
        "GN": 5,
        "degree_range": [
          4,
          5
        ],
        "domain_size_param": 0.1,
        "max_time": 45.0
      },
      "status": "launching",
      "log_file": "/home/scholten/globtimcore/hpc_results/minimal_4d_lv_test_GN=5_domain_size_param=0.1_max_time=45.0_20251002_100800/experiment.log",
      "cluster_node": "r04n02"
    },
    {
      "session_name": "minimal_4d_lv_test_GN=5_domain_size_param=0.15_max_time=45.0_20251002_100802",
      "parameters": {
        "GN": 5,
        "degree_range": [
          4,
          5
        ],
        "domain_size_param": 0.15,
        "max_time": 45.0
      },
      "status": "launching",
      "log_file": "/home/scholten/globtimcore/hpc_results/minimal_4d_lv_test_GN=5_domain_size_param=0.15_max_time=45.0_20251002_100802/experiment.log",
      "cluster_node": "r04n02"
    },
    {
      "session_name": "minimal_4d_lv_test_GN=5_domain_size_param=0.2_max_time=45.0_20251002_100810",
      "parameters": {
        "GN": 5,
        "degree_range": [
          4,
          5
        ],
        "domain_size_param": 0.2,
        "max_time": 45.0
      },
      "status": "launching",
      "log_file": "/home/scholten/globtimcore/hpc_results/minimal_4d_lv_test_GN=5_domain_size_param=0.2_max_time=45.0_20251002_100810/experiment.log",
      "cluster_node": "r04n02"
    },
    {
      "session_name": "minimal_4d_lv_test_GN=6_domain_size_param=0.1_max_time=45.0_20251002_100812",
      "parameters": {
        "GN": 6,
        "degree_range": [
          4,
          6
        ],
        "domain_size_param": 0.1,
        "max_time": 45.0
      },
      "status": "launching",
      "log_file": "/home/scholten/globtimcore/hpc_results/minimal_4d_lv_test_GN=6_domain_size_param=0.1_max_time=45.0_20251002_100812/experiment.log",
      "cluster_node": "r04n02"
    },
    {
      "session_name": "minimal_4d_lv_test_GN=6_domain_size_param=0.15_max_time=45.0_20251002_100813",
      "parameters": {
        "GN": 6,
        "degree_range": [
          4,
          6
        ],
        "domain_size_param": 0.15,
        "max_time": 45.0
      },
      "status": "launching",
      "log_file": "/home/scholten/globtimcore/hpc_results/minimal_4d_lv_test_GN=6_domain_size_param=0.15_max_time=45.0_20251002_100813/experiment.log",
      "cluster_node": "r04n02"
    },
    {
      "session_name": "minimal_4d_lv_test_GN=8_domain_size_param=0.1_max_time=45.0_20251002_100816",
      "parameters": {
        "GN": 8,
        "degree_range": [
          4,
          7
        ],
        "domain_size_param": 0.1,
        "max_time": 45.0
      },
      "status": "launching",
      "log_file": "/home/scholten/globtimcore/hpc_results/minimal_4d_lv_test_GN=8_domain_size_param=0.1_max_time=45.0_20251002_100816/experiment.log",
      "cluster_node": "r04n02"
    },
    {
      "session_name": "minimal_4d_lv_test_GN=8_domain_size_param=0.15_max_time=45.0_20251002_100818",
      "parameters": {
        "GN": 8,
        "degree_range": [
          4,
          7
        ],
        "domain_size_param": 0.15,
        "max_time": 45.0
      },
      "status": "launching",
      "log_file": "/home/scholten/globtimcore/hpc_results/minimal_4d_lv_test_GN=8_domain_size_param=0.15_max_time=45.0_20251002_100818/experiment.log",
      "cluster_node": "r04n02"
    }
  ]
}